{
  "session_id": "bot_random_search_captcha_0898_0_1777424592174",
  "image_id": "captcha_0898",
  "target_object": "shoes4",
  "result": "success",
  "duration": 2500,
  "click": {
    "x": 237,
    "y": 117,
    "t": 2500
  },
  "bbox": {
    "x": 200,
    "y": 80,
    "width": 75,
    "height": 75
  },
  "bot_type": "random_search",
  "mouse_logs": [
    {
      "t": 0,
      "x": 492,
      "y": 42
    },
    {
      "t": 57,
      "x": 691,
      "y": 97
    },
    {
      "t": 114,
      "x": 533,
      "y": 563
    },
    {
      "t": 170,
      "x": 321,
      "y": 26
    },
    {
      "t": 227,
      "x": 228,
      "y": 193
    },
    {
      "t": 284,
      "x": 410,
      "y": 397
    },
    {
      "t": 341,
      "x": 615,
      "y": 366
    },
    {
      "t": 398,
      "x": 254,
      "y": 590
    },
    {
      "t": 455,
      "x": 137,
      "y": 409
    },
    {
      "t": 511,
      "x": 614,
      "y": 10
    },
    {
      "t": 568,
      "x": 781,
      "y": 53
    },
    {
      "t": 625,
      "x": 738,
      "y": 197
    },
    {
      "t": 682,
      "x": 74,
      "y": 0
    },
    {
      "t": 739,
      "x": 253,
      "y": 112
    },
    {
      "t": 795,
      "x": 141,
      "y": 512
    },
    {
      "t": 852,
      "x": 387,
      "y": 552
    },
    {
      "t": 909,
      "x": 634,
      "y": 145
    },
    {
      "t": 966,
      "x": 689,
      "y": 225
    },
    {
      "t": 1023,
      "x": 212,
      "y": 10
    },
    {
      "t": 1080,
      "x": 278,
      "y": 285
    },
    {
      "t": 1136,
      "x": 390,
      "y": 547
    },
    {
      "t": 1193,
      "x": 443,
      "y": 580
    },
    {
      "t": 1250,
      "x": 617,
      "y": 391
    },
    {
      "t": 1307,
      "x": 461,
      "y": 150
    },
    {
      "t": 1364,
      "x": 185,
      "y": 541
    },
    {
      "t": 1420,
      "x": 795,
      "y": 283
    },
    {
      "t": 1477,
      "x": 686,
      "y": 412
    },
    {
      "t": 1534,
      "x": 36,
      "y": 63
    },
    {
      "t": 1591,
      "x": 485,
      "y": 415
    },
    {
      "t": 1648,
      "x": 137,
      "y": 66
    },
    {
      "t": 1705,
      "x": 523,
      "y": 446
    },
    {
      "t": 1761,
      "x": 339,
      "y": 297
    },
    {
      "t": 1818,
      "x": 287,
      "y": 340
    },
    {
      "t": 1875,
      "x": 162,
      "y": 296
    },
    {
      "t": 1932,
      "x": 334,
      "y": 138
    },
    {
      "t": 1989,
      "x": 160,
      "y": 560
    },
    {
      "t": 2045,
      "x": 520,
      "y": 228
    },
    {
      "t": 2102,
      "x": 379,
      "y": 572
    },
    {
      "t": 2159,
      "x": 537,
      "y": 7
    },
    {
      "t": 2216,
      "x": 380,
      "y": 7
    },
    {
      "t": 2273,
      "x": 718,
      "y": 285
    },
    {
      "t": 2330,
      "x": 687,
      "y": 302
    },
    {
      "t": 2386,
      "x": 408,
      "y": 386
    },
    {
      "t": 2443,
      "x": 396,
      "y": 200
    },
    {
      "t": 2500,
      "x": 237,
      "y": 117
    }
  ],
  "saved_at": "2026-04-29T10:03:12.174189"
}