{
  "session_id": "bot_random_search_captcha_0644_0_1777424587065",
  "image_id": "captcha_0644",
  "target_object": "cup3",
  "result": "success",
  "duration": 2500,
  "click": {
    "x": 313,
    "y": 227,
    "t": 2500
  },
  "bbox": {
    "x": 267,
    "y": 181,
    "width": 92,
    "height": 92
  },
  "bot_type": "random_search",
  "mouse_logs": [
    {
      "t": 0,
      "x": 335,
      "y": 523
    },
    {
      "t": 57,
      "x": 548,
      "y": 224
    },
    {
      "t": 114,
      "x": 279,
      "y": 368
    },
    {
      "t": 170,
      "x": 521,
      "y": 595
    },
    {
      "t": 227,
      "x": 98,
      "y": 255
    },
    {
      "t": 284,
      "x": 117,
      "y": 50
    },
    {
      "t": 341,
      "x": 340,
      "y": 138
    },
    {
      "t": 398,
      "x": 691,
      "y": 53
    },
    {
      "t": 455,
      "x": 278,
      "y": 354
    },
    {
      "t": 511,
      "x": 236,
      "y": 130
    },
    {
      "t": 568,
      "x": 565,
      "y": 562
    },
    {
      "t": 625,
      "x": 399,
      "y": 17
    },
    {
      "t": 682,
      "x": 534,
      "y": 152
    },
    {
      "t": 739,
      "x": 155,
      "y": 298
    },
    {
      "t": 795,
      "x": 744,
      "y": 574
    },
    {
      "t": 852,
      "x": 603,
      "y": 53
    },
    {
      "t": 909,
      "x": 796,
      "y": 263
    },
    {
      "t": 966,
      "x": 235,
      "y": 157
    },
    {
      "t": 1023,
      "x": 30,
      "y": 124
    },
    {
      "t": 1080,
      "x": 632,
      "y": 414
    },
    {
      "t": 1136,
      "x": 440,
      "y": 521
    },
    {
      "t": 1193,
      "x": 276,
      "y": 435
    },
    {
      "t": 1250,
      "x": 639,
      "y": 565
    },
    {
      "t": 1307,
      "x": 680,
      "y": 116
    },
    {
      "t": 1364,
      "x": 498,
      "y": 599
    },
    {
      "t": 1420,
      "x": 394,
      "y": 386
    },
    {
      "t": 1477,
      "x": 398,
      "y": 28
    },
    {
      "t": 1534,
      "x": 272,
      "y": 196
    },
    {
      "t": 1591,
      "x": 21,
      "y": 182
    },
    {
      "t": 1648,
      "x": 217,
      "y": 42
    },
    {
      "t": 1705,
      "x": 770,
      "y": 522
    },
    {
      "t": 1761,
      "x": 613,
      "y": 320
    },
    {
      "t": 1818,
      "x": 265,
      "y": 45
    },
    {
      "t": 1875,
      "x": 623,
      "y": 230
    },
    {
      "t": 1932,
      "x": 742,
      "y": 91
    },
    {
      "t": 1989,
      "x": 378,
      "y": 219
    },
    {
      "t": 2045,
      "x": 609,
      "y": 267
    },
    {
      "t": 2102,
      "x": 502,
      "y": 340
    },
    {
      "t": 2159,
      "x": 608,
      "y": 415
    },
    {
      "t": 2216,
      "x": 165,
      "y": 138
    },
    {
      "t": 2273,
      "x": 202,
      "y": 469
    },
    {
      "t": 2330,
      "x": 481,
      "y": 488
    },
    {
      "t": 2386,
      "x": 41,
      "y": 78
    },
    {
      "t": 2443,
      "x": 638,
      "y": 320
    },
    {
      "t": 2500,
      "x": 313,
      "y": 227
    }
  ],
  "saved_at": "2026-04-29T10:03:07.065448"
}