{
  "session_id": "bot_random_search_captcha_0367_0_1777424581929",
  "image_id": "captcha_0367",
  "target_object": "라이언",
  "result": "success",
  "duration": 2500,
  "click": {
    "x": 482,
    "y": 162,
    "t": 2500
  },
  "bbox": {
    "x": 438,
    "y": 110,
    "width": 88,
    "height": 104
  },
  "bot_type": "random_search",
  "mouse_logs": [
    {
      "t": 0,
      "x": 231,
      "y": 127
    },
    {
      "t": 57,
      "x": 725,
      "y": 97
    },
    {
      "t": 114,
      "x": 518,
      "y": 420
    },
    {
      "t": 170,
      "x": 694,
      "y": 224
    },
    {
      "t": 227,
      "x": 701,
      "y": 263
    },
    {
      "t": 284,
      "x": 318,
      "y": 573
    },
    {
      "t": 341,
      "x": 263,
      "y": 92
    },
    {
      "t": 398,
      "x": 684,
      "y": 90
    },
    {
      "t": 455,
      "x": 253,
      "y": 65
    },
    {
      "t": 511,
      "x": 783,
      "y": 132
    },
    {
      "t": 568,
      "x": 742,
      "y": 124
    },
    {
      "t": 625,
      "x": 644,
      "y": 126
    },
    {
      "t": 682,
      "x": 327,
      "y": 425
    },
    {
      "t": 739,
      "x": 357,
      "y": 109
    },
    {
      "t": 795,
      "x": 768,
      "y": 106
    },
    {
      "t": 852,
      "x": 258,
      "y": 265
    },
    {
      "t": 909,
      "x": 215,
      "y": 488
    },
    {
      "t": 966,
      "x": 733,
      "y": 330
    },
    {
      "t": 1023,
      "x": 172,
      "y": 48
    },
    {
      "t": 1080,
      "x": 772,
      "y": 105
    },
    {
      "t": 1136,
      "x": 340,
      "y": 302
    },
    {
      "t": 1193,
      "x": 321,
      "y": 539
    },
    {
      "t": 1250,
      "x": 427,
      "y": 136
    },
    {
      "t": 1307,
      "x": 372,
      "y": 37
    },
    {
      "t": 1364,
      "x": 259,
      "y": 391
    },
    {
      "t": 1420,
      "x": 15,
      "y": 240
    },
    {
      "t": 1477,
      "x": 103,
      "y": 191
    },
    {
      "t": 1534,
      "x": 267,
      "y": 42
    },
    {
      "t": 1591,
      "x": 172,
      "y": 168
    },
    {
      "t": 1648,
      "x": 633,
      "y": 308
    },
    {
      "t": 1705,
      "x": 519,
      "y": 560
    },
    {
      "t": 1761,
      "x": 763,
      "y": 127
    },
    {
      "t": 1818,
      "x": 377,
      "y": 104
    },
    {
      "t": 1875,
      "x": 319,
      "y": 61
    },
    {
      "t": 1932,
      "x": 778,
      "y": 236
    },
    {
      "t": 1989,
      "x": 74,
      "y": 538
    },
    {
      "t": 2045,
      "x": 102,
      "y": 433
    },
    {
      "t": 2102,
      "x": 296,
      "y": 596
    },
    {
      "t": 2159,
      "x": 773,
      "y": 460
    },
    {
      "t": 2216,
      "x": 152,
      "y": 551
    },
    {
      "t": 2273,
      "x": 614,
      "y": 592
    },
    {
      "t": 2330,
      "x": 188,
      "y": 512
    },
    {
      "t": 2386,
      "x": 445,
      "y": 145
    },
    {
      "t": 2443,
      "x": 73,
      "y": 102
    },
    {
      "t": 2500,
      "x": 482,
      "y": 162
    }
  ],
  "saved_at": "2026-04-29T10:03:01.929591"
}