{
  "session_id": "bot_random_search_captcha_0533_1_1777424585098",
  "image_id": "captcha_0533",
  "target_object": "key1",
  "result": "success",
  "duration": 2500,
  "click": {
    "x": 606,
    "y": 308,
    "t": 2500
  },
  "bbox": {
    "x": 572,
    "y": 274,
    "width": 68,
    "height": 68
  },
  "bot_type": "random_search",
  "mouse_logs": [
    {
      "t": 0,
      "x": 153,
      "y": 315
    },
    {
      "t": 57,
      "x": 766,
      "y": 420
    },
    {
      "t": 114,
      "x": 607,
      "y": 560
    },
    {
      "t": 170,
      "x": 486,
      "y": 285
    },
    {
      "t": 227,
      "x": 341,
      "y": 188
    },
    {
      "t": 284,
      "x": 800,
      "y": 102
    },
    {
      "t": 341,
      "x": 152,
      "y": 436
    },
    {
      "t": 398,
      "x": 74,
      "y": 240
    },
    {
      "t": 455,
      "x": 642,
      "y": 374
    },
    {
      "t": 511,
      "x": 730,
      "y": 348
    },
    {
      "t": 568,
      "x": 745,
      "y": 10
    },
    {
      "t": 625,
      "x": 697,
      "y": 291
    },
    {
      "t": 682,
      "x": 331,
      "y": 101
    },
    {
      "t": 739,
      "x": 458,
      "y": 193
    },
    {
      "t": 795,
      "x": 693,
      "y": 242
    },
    {
      "t": 852,
      "x": 32,
      "y": 274
    },
    {
      "t": 909,
      "x": 278,
      "y": 338
    },
    {
      "t": 966,
      "x": 369,
      "y": 97
    },
    {
      "t": 1023,
      "x": 472,
      "y": 524
    },
    {
      "t": 1080,
      "x": 564,
      "y": 177
    },
    {
      "t": 1136,
      "x": 595,
      "y": 143
    },
    {
      "t": 1193,
      "x": 405,
      "y": 84
    },
    {
      "t": 1250,
      "x": 611,
      "y": 171
    },
    {
      "t": 1307,
      "x": 267,
      "y": 448
    },
    {
      "t": 1364,
      "x": 33,
      "y": 513
    },
    {
      "t": 1420,
      "x": 718,
      "y": 412
    },
    {
      "t": 1477,
      "x": 110,
      "y": 345
    },
    {
      "t": 1534,
      "x": 353,
      "y": 167
    },
    {
      "t": 1591,
      "x": 728,
      "y": 125
    },
    {
      "t": 1648,
      "x": 643,
      "y": 198
    },
    {
      "t": 1705,
      "x": 317,
      "y": 568
    },
    {
      "t": 1761,
      "x": 357,
      "y": 411
    },
    {
      "t": 1818,
      "x": 399,
      "y": 509
    },
    {
      "t": 1875,
      "x": 655,
      "y": 340
    },
    {
      "t": 1932,
      "x": 296,
      "y": 580
    },
    {
      "t": 1989,
      "x": 743,
      "y": 109
    },
    {
      "t": 2045,
      "x": 267,
      "y": 128
    },
    {
      "t": 2102,
      "x": 545,
      "y": 253
    },
    {
      "t": 2159,
      "x": 765,
      "y": 484
    },
    {
      "t": 2216,
      "x": 418,
      "y": 234
    },
    {
      "t": 2273,
      "x": 333,
      "y": 449
    },
    {
      "t": 2330,
      "x": 76,
      "y": 407
    },
    {
      "t": 2386,
      "x": 371,
      "y": 478
    },
    {
      "t": 2443,
      "x": 628,
      "y": 527
    },
    {
      "t": 2500,
      "x": 606,
      "y": 308
    }
  ],
  "saved_at": "2026-04-29T10:03:05.098347"
}