{
  "session_id": "bot_random_search_captcha_0407_0_1777424582610",
  "image_id": "captcha_0407",
  "target_object": "shoes2",
  "result": "success",
  "duration": 2500,
  "click": {
    "x": 458,
    "y": 241,
    "t": 2500
  },
  "bbox": {
    "x": 419,
    "y": 202,
    "width": 78,
    "height": 78
  },
  "bot_type": "random_search",
  "mouse_logs": [
    {
      "t": 0,
      "x": 200,
      "y": 121
    },
    {
      "t": 57,
      "x": 68,
      "y": 572
    },
    {
      "t": 114,
      "x": 129,
      "y": 279
    },
    {
      "t": 170,
      "x": 196,
      "y": 460
    },
    {
      "t": 227,
      "x": 222,
      "y": 415
    },
    {
      "t": 284,
      "x": 207,
      "y": 349
    },
    {
      "t": 341,
      "x": 214,
      "y": 433
    },
    {
      "t": 398,
      "x": 377,
      "y": 24
    },
    {
      "t": 455,
      "x": 248,
      "y": 15
    },
    {
      "t": 511,
      "x": 582,
      "y": 319
    },
    {
      "t": 568,
      "x": 159,
      "y": 63
    },
    {
      "t": 625,
      "x": 456,
      "y": 443
    },
    {
      "t": 682,
      "x": 61,
      "y": 156
    },
    {
      "t": 739,
      "x": 590,
      "y": 387
    },
    {
      "t": 795,
      "x": 591,
      "y": 139
    },
    {
      "t": 852,
      "x": 610,
      "y": 597
    },
    {
      "t": 909,
      "x": 150,
      "y": 353
    },
    {
      "t": 966,
      "x": 731,
      "y": 167
    },
    {
      "t": 1023,
      "x": 614,
      "y": 429
    },
    {
      "t": 1080,
      "x": 337,
      "y": 495
    },
    {
      "t": 1136,
      "x": 189,
      "y": 109
    },
    {
      "t": 1193,
      "x": 262,
      "y": 352
    },
    {
      "t": 1250,
      "x": 242,
      "y": 125
    },
    {
      "t": 1307,
      "x": 223,
      "y": 377
    },
    {
      "t": 1364,
      "x": 139,
      "y": 132
    },
    {
      "t": 1420,
      "x": 498,
      "y": 315
    },
    {
      "t": 1477,
      "x": 37,
      "y": 585
    },
    {
      "t": 1534,
      "x": 224,
      "y": 187
    },
    {
      "t": 1591,
      "x": 488,
      "y": 233
    },
    {
      "t": 1648,
      "x": 724,
      "y": 584
    },
    {
      "t": 1705,
      "x": 650,
      "y": 99
    },
    {
      "t": 1761,
      "x": 403,
      "y": 302
    },
    {
      "t": 1818,
      "x": 314,
      "y": 365
    },
    {
      "t": 1875,
      "x": 47,
      "y": 343
    },
    {
      "t": 1932,
      "x": 606,
      "y": 447
    },
    {
      "t": 1989,
      "x": 108,
      "y": 37
    },
    {
      "t": 2045,
      "x": 292,
      "y": 488
    },
    {
      "t": 2102,
      "x": 462,
      "y": 553
    },
    {
      "t": 2159,
      "x": 742,
      "y": 96
    },
    {
      "t": 2216,
      "x": 373,
      "y": 560
    },
    {
      "t": 2273,
      "x": 106,
      "y": 2
    },
    {
      "t": 2330,
      "x": 611,
      "y": 1
    },
    {
      "t": 2386,
      "x": 513,
      "y": 391
    },
    {
      "t": 2443,
      "x": 297,
      "y": 269
    },
    {
      "t": 2500,
      "x": 458,
      "y": 241
    }
  ],
  "saved_at": "2026-04-29T10:03:02.610971"
}