{
  "session_id": "bot_random_search_captcha_0090_2_1777424576869",
  "image_id": "captcha_0090",
  "target_object": "key2",
  "result": "success",
  "duration": 2500,
  "click": {
    "x": 713,
    "y": 315,
    "t": 2500
  },
  "bbox": {
    "x": 685,
    "y": 287,
    "width": 57,
    "height": 57
  },
  "bot_type": "random_search",
  "mouse_logs": [
    {
      "t": 0,
      "x": 662,
      "y": 370
    },
    {
      "t": 57,
      "x": 317,
      "y": 93
    },
    {
      "t": 114,
      "x": 701,
      "y": 140
    },
    {
      "t": 170,
      "x": 564,
      "y": 529
    },
    {
      "t": 227,
      "x": 703,
      "y": 525
    },
    {
      "t": 284,
      "x": 168,
      "y": 235
    },
    {
      "t": 341,
      "x": 553,
      "y": 231
    },
    {
      "t": 398,
      "x": 355,
      "y": 251
    },
    {
      "t": 455,
      "x": 42,
      "y": 595
    },
    {
      "t": 511,
      "x": 733,
      "y": 589
    },
    {
      "t": 568,
      "x": 74,
      "y": 497
    },
    {
      "t": 625,
      "x": 38,
      "y": 415
    },
    {
      "t": 682,
      "x": 229,
      "y": 246
    },
    {
      "t": 739,
      "x": 375,
      "y": 491
    },
    {
      "t": 795,
      "x": 420,
      "y": 392
    },
    {
      "t": 852,
      "x": 603,
      "y": 396
    },
    {
      "t": 909,
      "x": 564,
      "y": 50
    },
    {
      "t": 966,
      "x": 786,
      "y": 571
    },
    {
      "t": 1023,
      "x": 98,
      "y": 259
    },
    {
      "t": 1080,
      "x": 678,
      "y": 375
    },
    {
      "t": 1136,
      "x": 620,
      "y": 207
    },
    {
      "t": 1193,
      "x": 748,
      "y": 548
    },
    {
      "t": 1250,
      "x": 368,
      "y": 97
    },
    {
      "t": 1307,
      "x": 642,
      "y": 256
    },
    {
      "t": 1364,
      "x": 216,
      "y": 52
    },
    {
      "t": 1420,
      "x": 727,
      "y": 349
    },
    {
      "t": 1477,
      "x": 774,
      "y": 129
    },
    {
      "t": 1534,
      "x": 18,
      "y": 86
    },
    {
      "t": 1591,
      "x": 280,
      "y": 407
    },
    {
      "t": 1648,
      "x": 669,
      "y": 183
    },
    {
      "t": 1705,
      "x": 692,
      "y": 536
    },
    {
      "t": 1761,
      "x": 776,
      "y": 163
    },
    {
      "t": 1818,
      "x": 654,
      "y": 273
    },
    {
      "t": 1875,
      "x": 789,
      "y": 407
    },
    {
      "t": 1932,
      "x": 608,
      "y": 501
    },
    {
      "t": 1989,
      "x": 319,
      "y": 433
    },
    {
      "t": 2045,
      "x": 786,
      "y": 387
    },
    {
      "t": 2102,
      "x": 752,
      "y": 56
    },
    {
      "t": 2159,
      "x": 44,
      "y": 207
    },
    {
      "t": 2216,
      "x": 604,
      "y": 135
    },
    {
      "t": 2273,
      "x": 156,
      "y": 88
    },
    {
      "t": 2330,
      "x": 472,
      "y": 386
    },
    {
      "t": 2386,
      "x": 520,
      "y": 134
    },
    {
      "t": 2443,
      "x": 582,
      "y": 205
    },
    {
      "t": 2500,
      "x": 713,
      "y": 315
    }
  ],
  "saved_at": "2026-04-29T10:02:56.869979"
}