{
  "session_id": "bot_random_search_captcha_0312_2_1777424580981",
  "image_id": "captcha_0312",
  "target_object": "cup2",
  "result": "success",
  "duration": 2500,
  "click": {
    "x": 104,
    "y": 423,
    "t": 2500
  },
  "bbox": {
    "x": 56,
    "y": 375,
    "width": 96,
    "height": 96
  },
  "bot_type": "random_search",
  "mouse_logs": [
    {
      "t": 0,
      "x": 651,
      "y": 32
    },
    {
      "t": 57,
      "x": 542,
      "y": 8
    },
    {
      "t": 114,
      "x": 38,
      "y": 2
    },
    {
      "t": 170,
      "x": 732,
      "y": 336
    },
    {
      "t": 227,
      "x": 532,
      "y": 355
    },
    {
      "t": 284,
      "x": 572,
      "y": 183
    },
    {
      "t": 341,
      "x": 657,
      "y": 513
    },
    {
      "t": 398,
      "x": 526,
      "y": 50
    },
    {
      "t": 455,
      "x": 748,
      "y": 268
    },
    {
      "t": 511,
      "x": 495,
      "y": 49
    },
    {
      "t": 568,
      "x": 573,
      "y": 69
    },
    {
      "t": 625,
      "x": 622,
      "y": 418
    },
    {
      "t": 682,
      "x": 222,
      "y": 371
    },
    {
      "t": 739,
      "x": 720,
      "y": 266
    },
    {
      "t": 795,
      "x": 439,
      "y": 22
    },
    {
      "t": 852,
      "x": 218,
      "y": 129
    },
    {
      "t": 909,
      "x": 522,
      "y": 133
    },
    {
      "t": 966,
      "x": 103,
      "y": 148
    },
    {
      "t": 1023,
      "x": 275,
      "y": 517
    },
    {
      "t": 1080,
      "x": 231,
      "y": 42
    },
    {
      "t": 1136,
      "x": 432,
      "y": 172
    },
    {
      "t": 1193,
      "x": 142,
      "y": 44
    },
    {
      "t": 1250,
      "x": 375,
      "y": 533
    },
    {
      "t": 1307,
      "x": 383,
      "y": 110
    },
    {
      "t": 1364,
      "x": 687,
      "y": 159
    },
    {
      "t": 1420,
      "x": 551,
      "y": 235
    },
    {
      "t": 1477,
      "x": 717,
      "y": 524
    },
    {
      "t": 1534,
      "x": 445,
      "y": 237
    },
    {
      "t": 1591,
      "x": 590,
      "y": 128
    },
    {
      "t": 1648,
      "x": 659,
      "y": 59
    },
    {
      "t": 1705,
      "x": 794,
      "y": 306
    },
    {
      "t": 1761,
      "x": 88,
      "y": 595
    },
    {
      "t": 1818,
      "x": 99,
      "y": 187
    },
    {
      "t": 1875,
      "x": 438,
      "y": 531
    },
    {
      "t": 1932,
      "x": 73,
      "y": 72
    },
    {
      "t": 1989,
      "x": 679,
      "y": 32
    },
    {
      "t": 2045,
      "x": 119,
      "y": 196
    },
    {
      "t": 2102,
      "x": 270,
      "y": 264
    },
    {
      "t": 2159,
      "x": 491,
      "y": 300
    },
    {
      "t": 2216,
      "x": 250,
      "y": 166
    },
    {
      "t": 2273,
      "x": 764,
      "y": 78
    },
    {
      "t": 2330,
      "x": 746,
      "y": 315
    },
    {
      "t": 2386,
      "x": 263,
      "y": 332
    },
    {
      "t": 2443,
      "x": 530,
      "y": 181
    },
    {
      "t": 2500,
      "x": 104,
      "y": 423
    }
  ],
  "saved_at": "2026-04-29T10:03:00.981702"
}