{
  "session_id": "bot_random_search_captcha_0645_1_1777424587081",
  "image_id": "captcha_0645",
  "target_object": "춘식이",
  "result": "success",
  "duration": 2500,
  "click": {
    "x": 127,
    "y": 405,
    "t": 2500
  },
  "bbox": {
    "x": 52,
    "y": 330,
    "width": 151,
    "height": 151
  },
  "bot_type": "random_search",
  "mouse_logs": [
    {
      "t": 0,
      "x": 676,
      "y": 230
    },
    {
      "t": 57,
      "x": 691,
      "y": 11
    },
    {
      "t": 114,
      "x": 256,
      "y": 194
    },
    {
      "t": 170,
      "x": 519,
      "y": 226
    },
    {
      "t": 227,
      "x": 510,
      "y": 6
    },
    {
      "t": 284,
      "x": 738,
      "y": 470
    },
    {
      "t": 341,
      "x": 568,
      "y": 557
    },
    {
      "t": 398,
      "x": 302,
      "y": 545
    },
    {
      "t": 455,
      "x": 539,
      "y": 526
    },
    {
      "t": 511,
      "x": 369,
      "y": 145
    },
    {
      "t": 568,
      "x": 426,
      "y": 509
    },
    {
      "t": 625,
      "x": 636,
      "y": 289
    },
    {
      "t": 682,
      "x": 147,
      "y": 189
    },
    {
      "t": 739,
      "x": 780,
      "y": 525
    },
    {
      "t": 795,
      "x": 122,
      "y": 314
    },
    {
      "t": 852,
      "x": 174,
      "y": 216
    },
    {
      "t": 909,
      "x": 748,
      "y": 123
    },
    {
      "t": 966,
      "x": 475,
      "y": 425
    },
    {
      "t": 1023,
      "x": 213,
      "y": 335
    },
    {
      "t": 1080,
      "x": 629,
      "y": 6
    },
    {
      "t": 1136,
      "x": 83,
      "y": 457
    },
    {
      "t": 1193,
      "x": 605,
      "y": 563
    },
    {
      "t": 1250,
      "x": 548,
      "y": 98
    },
    {
      "t": 1307,
      "x": 551,
      "y": 343
    },
    {
      "t": 1364,
      "x": 285,
      "y": 204
    },
    {
      "t": 1420,
      "x": 549,
      "y": 419
    },
    {
      "t": 1477,
      "x": 36,
      "y": 299
    },
    {
      "t": 1534,
      "x": 730,
      "y": 79
    },
    {
      "t": 1591,
      "x": 366,
      "y": 340
    },
    {
      "t": 1648,
      "x": 35,
      "y": 580
    },
    {
      "t": 1705,
      "x": 281,
      "y": 50
    },
    {
      "t": 1761,
      "x": 123,
      "y": 418
    },
    {
      "t": 1818,
      "x": 672,
      "y": 268
    },
    {
      "t": 1875,
      "x": 509,
      "y": 219
    },
    {
      "t": 1932,
      "x": 237,
      "y": 4
    },
    {
      "t": 1989,
      "x": 437,
      "y": 54
    },
    {
      "t": 2045,
      "x": 110,
      "y": 103
    },
    {
      "t": 2102,
      "x": 757,
      "y": 337
    },
    {
      "t": 2159,
      "x": 546,
      "y": 554
    },
    {
      "t": 2216,
      "x": 407,
      "y": 58
    },
    {
      "t": 2273,
      "x": 269,
      "y": 237
    },
    {
      "t": 2330,
      "x": 720,
      "y": 442
    },
    {
      "t": 2386,
      "x": 581,
      "y": 157
    },
    {
      "t": 2443,
      "x": 232,
      "y": 33
    },
    {
      "t": 2500,
      "x": 127,
      "y": 405
    }
  ],
  "saved_at": "2026-04-29T10:03:07.081142"
}