{
  "session_id": "bot_known_target_captcha_0684_1_1777424587806",
  "image_id": "captcha_0684",
  "target_object": "key5",
  "result": "success",
  "duration": 900,
  "click": {
    "x": 601,
    "y": 130,
    "t": 900
  },
  "bbox": {
    "x": 549,
    "y": 78,
    "width": 105,
    "height": 105
  },
  "bot_type": "known_target",
  "mouse_logs": [
    {
      "t": 0,
      "x": 774,
      "y": 475
    },
    {
      "t": 53,
      "x": 764,
      "y": 455
    },
    {
      "t": 106,
      "x": 754,
      "y": 434
    },
    {
      "t": 159,
      "x": 743,
      "y": 414
    },
    {
      "t": 212,
      "x": 733,
      "y": 394
    },
    {
      "t": 265,
      "x": 723,
      "y": 374
    },
    {
      "t": 318,
      "x": 713,
      "y": 353
    },
    {
      "t": 371,
      "x": 703,
      "y": 333
    },
    {
      "t": 424,
      "x": 693,
      "y": 313
    },
    {
      "t": 476,
      "x": 682,
      "y": 292
    },
    {
      "t": 529,
      "x": 672,
      "y": 272
    },
    {
      "t": 582,
      "x": 662,
      "y": 252
    },
    {
      "t": 635,
      "x": 652,
      "y": 231
    },
    {
      "t": 688,
      "x": 642,
      "y": 211
    },
    {
      "t": 741,
      "x": 632,
      "y": 191
    },
    {
      "t": 794,
      "x": 621,
      "y": 171
    },
    {
      "t": 847,
      "x": 611,
      "y": 150
    },
    {
      "t": 900,
      "x": 601,
      "y": 130
    }
  ],
  "saved_at": "2026-04-29T10:03:07.806581"
}