{
  "session_id": "bot_known_target_captcha_0058_2_1777424576304",
  "image_id": "captcha_0058",
  "target_object": "key3",
  "result": "success",
  "duration": 900,
  "click": {
    "x": 406,
    "y": 70,
    "t": 900
  },
  "bbox": {
    "x": 373,
    "y": 37,
    "width": 67,
    "height": 67
  },
  "bot_type": "known_target",
  "mouse_logs": [
    {
      "t": 0,
      "x": 354,
      "y": 589
    },
    {
      "t": 53,
      "x": 357,
      "y": 558
    },
    {
      "t": 106,
      "x": 360,
      "y": 528
    },
    {
      "t": 159,
      "x": 363,
      "y": 497
    },
    {
      "t": 212,
      "x": 366,
      "y": 467
    },
    {
      "t": 265,
      "x": 369,
      "y": 436
    },
    {
      "t": 318,
      "x": 372,
      "y": 406
    },
    {
      "t": 371,
      "x": 375,
      "y": 375
    },
    {
      "t": 424,
      "x": 378,
      "y": 345
    },
    {
      "t": 476,
      "x": 382,
      "y": 314
    },
    {
      "t": 529,
      "x": 385,
      "y": 284
    },
    {
      "t": 582,
      "x": 388,
      "y": 253
    },
    {
      "t": 635,
      "x": 391,
      "y": 223
    },
    {
      "t": 688,
      "x": 394,
      "y": 192
    },
    {
      "t": 741,
      "x": 397,
      "y": 162
    },
    {
      "t": 794,
      "x": 400,
      "y": 131
    },
    {
      "t": 847,
      "x": 403,
      "y": 101
    },
    {
      "t": 900,
      "x": 406,
      "y": 70
    }
  ],
  "saved_at": "2026-04-29T10:02:56.304427"
}