{
  "session_id": "bot_known_target_captcha_0035_1_1777424575860",
  "image_id": "captcha_0035",
  "target_object": "cup4",
  "result": "success",
  "duration": 900,
  "click": {
    "x": 383,
    "y": 369,
    "t": 900
  },
  "bbox": {
    "x": 342,
    "y": 328,
    "width": 83,
    "height": 83
  },
  "bot_type": "known_target",
  "mouse_logs": [
    {
      "t": 0,
      "x": 151,
      "y": 169
    },
    {
      "t": 53,
      "x": 165,
      "y": 181
    },
    {
      "t": 106,
      "x": 178,
      "y": 193
    },
    {
      "t": 159,
      "x": 192,
      "y": 204
    },
    {
      "t": 212,
      "x": 206,
      "y": 216
    },
    {
      "t": 265,
      "x": 219,
      "y": 228
    },
    {
      "t": 318,
      "x": 233,
      "y": 240
    },
    {
      "t": 371,
      "x": 247,
      "y": 251
    },
    {
      "t": 424,
      "x": 260,
      "y": 263
    },
    {
      "t": 476,
      "x": 274,
      "y": 275
    },
    {
      "t": 529,
      "x": 287,
      "y": 287
    },
    {
      "t": 582,
      "x": 301,
      "y": 298
    },
    {
      "t": 635,
      "x": 315,
      "y": 310
    },
    {
      "t": 688,
      "x": 328,
      "y": 322
    },
    {
      "t": 741,
      "x": 342,
      "y": 334
    },
    {
      "t": 794,
      "x": 356,
      "y": 345
    },
    {
      "t": 847,
      "x": 369,
      "y": 357
    },
    {
      "t": 900,
      "x": 383,
      "y": 369
    }
  ],
  "saved_at": "2026-04-29T10:02:55.860992"
}