{
  "session_id": "bot_known_target_captcha_0282_2_1777424580427",
  "image_id": "captcha_0282",
  "target_object": "무지",
  "result": "success",
  "duration": 900,
  "click": {
    "x": 188,
    "y": 373,
    "t": 900
  },
  "bbox": {
    "x": 114,
    "y": 299,
    "width": 149,
    "height": 149
  },
  "bot_type": "known_target",
  "mouse_logs": [
    {
      "t": 0,
      "x": 602,
      "y": 130
    },
    {
      "t": 53,
      "x": 578,
      "y": 144
    },
    {
      "t": 106,
      "x": 553,
      "y": 159
    },
    {
      "t": 159,
      "x": 529,
      "y": 173
    },
    {
      "t": 212,
      "x": 505,
      "y": 187
    },
    {
      "t": 265,
      "x": 480,
      "y": 201
    },
    {
      "t": 318,
      "x": 456,
      "y": 216
    },
    {
      "t": 371,
      "x": 432,
      "y": 230
    },
    {
      "t": 424,
      "x": 407,
      "y": 244
    },
    {
      "t": 476,
      "x": 383,
      "y": 259
    },
    {
      "t": 529,
      "x": 358,
      "y": 273
    },
    {
      "t": 582,
      "x": 334,
      "y": 287
    },
    {
      "t": 635,
      "x": 310,
      "y": 302
    },
    {
      "t": 688,
      "x": 285,
      "y": 316
    },
    {
      "t": 741,
      "x": 261,
      "y": 330
    },
    {
      "t": 794,
      "x": 237,
      "y": 344
    },
    {
      "t": 847,
      "x": 212,
      "y": 359
    },
    {
      "t": 900,
      "x": 188,
      "y": 373
    }
  ],
  "saved_at": "2026-04-29T10:03:00.427287"
}