{
  "session_id": "bot_known_target_captcha_0759_1_1777424589506",
  "image_id": "captcha_0759",
  "target_object": "shoes4",
  "result": "success",
  "duration": 900,
  "click": {
    "x": 123,
    "y": 330,
    "t": 900
  },
  "bbox": {
    "x": 76,
    "y": 283,
    "width": 94,
    "height": 94
  },
  "bot_type": "known_target",
  "mouse_logs": [
    {
      "t": 0,
      "x": 159,
      "y": 558
    },
    {
      "t": 53,
      "x": 157,
      "y": 545
    },
    {
      "t": 106,
      "x": 155,
      "y": 531
    },
    {
      "t": 159,
      "x": 153,
      "y": 518
    },
    {
      "t": 212,
      "x": 151,
      "y": 504
    },
    {
      "t": 265,
      "x": 148,
      "y": 491
    },
    {
      "t": 318,
      "x": 146,
      "y": 478
    },
    {
      "t": 371,
      "x": 144,
      "y": 464
    },
    {
      "t": 424,
      "x": 142,
      "y": 451
    },
    {
      "t": 476,
      "x": 140,
      "y": 437
    },
    {
      "t": 529,
      "x": 138,
      "y": 424
    },
    {
      "t": 582,
      "x": 136,
      "y": 410
    },
    {
      "t": 635,
      "x": 134,
      "y": 397
    },
    {
      "t": 688,
      "x": 131,
      "y": 384
    },
    {
      "t": 741,
      "x": 129,
      "y": 370
    },
    {
      "t": 794,
      "x": 127,
      "y": 357
    },
    {
      "t": 847,
      "x": 125,
      "y": 343
    },
    {
      "t": 900,
      "x": 123,
      "y": 330
    }
  ],
  "saved_at": "2026-04-29T10:03:09.506673"
}