{
  "session_id": "bot_known_target_captcha_0219_0_1777424579340",
  "image_id": "captcha_0219",
  "target_object": "shoes5",
  "result": "success",
  "duration": 900,
  "click": {
    "x": 492,
    "y": 183,
    "t": 900
  },
  "bbox": {
    "x": 458,
    "y": 158,
    "width": 68,
    "height": 50
  },
  "bot_type": "known_target",
  "mouse_logs": [
    {
      "t": 0,
      "x": 466,
      "y": 282
    },
    {
      "t": 53,
      "x": 468,
      "y": 276
    },
    {
      "t": 106,
      "x": 469,
      "y": 270
    },
    {
      "t": 159,
      "x": 471,
      "y": 265
    },
    {
      "t": 212,
      "x": 472,
      "y": 259
    },
    {
      "t": 265,
      "x": 474,
      "y": 253
    },
    {
      "t": 318,
      "x": 475,
      "y": 247
    },
    {
      "t": 371,
      "x": 477,
      "y": 241
    },
    {
      "t": 424,
      "x": 478,
      "y": 235
    },
    {
      "t": 476,
      "x": 480,
      "y": 230
    },
    {
      "t": 529,
      "x": 481,
      "y": 224
    },
    {
      "t": 582,
      "x": 483,
      "y": 218
    },
    {
      "t": 635,
      "x": 484,
      "y": 212
    },
    {
      "t": 688,
      "x": 486,
      "y": 206
    },
    {
      "t": 741,
      "x": 487,
      "y": 200
    },
    {
      "t": 794,
      "x": 489,
      "y": 195
    },
    {
      "t": 847,
      "x": 490,
      "y": 189
    },
    {
      "t": 900,
      "x": 492,
      "y": 183
    }
  ],
  "saved_at": "2026-04-29T10:02:59.340471"
}