{
  "session_id": "bot_known_target_captcha_0304_2_1777424580814",
  "image_id": "captcha_0304",
  "target_object": "key4",
  "result": "success",
  "duration": 900,
  "click": {
    "x": 478,
    "y": 316,
    "t": 900
  },
  "bbox": {
    "x": 405,
    "y": 242,
    "width": 147,
    "height": 148
  },
  "bot_type": "known_target",
  "mouse_logs": [
    {
      "t": 0,
      "x": 612,
      "y": 210
    },
    {
      "t": 53,
      "x": 604,
      "y": 216
    },
    {
      "t": 106,
      "x": 596,
      "y": 222
    },
    {
      "t": 159,
      "x": 588,
      "y": 229
    },
    {
      "t": 212,
      "x": 580,
      "y": 235
    },
    {
      "t": 265,
      "x": 573,
      "y": 241
    },
    {
      "t": 318,
      "x": 565,
      "y": 247
    },
    {
      "t": 371,
      "x": 557,
      "y": 254
    },
    {
      "t": 424,
      "x": 549,
      "y": 260
    },
    {
      "t": 476,
      "x": 541,
      "y": 266
    },
    {
      "t": 529,
      "x": 533,
      "y": 272
    },
    {
      "t": 582,
      "x": 525,
      "y": 279
    },
    {
      "t": 635,
      "x": 517,
      "y": 285
    },
    {
      "t": 688,
      "x": 510,
      "y": 291
    },
    {
      "t": 741,
      "x": 502,
      "y": 297
    },
    {
      "t": 794,
      "x": 494,
      "y": 304
    },
    {
      "t": 847,
      "x": 486,
      "y": 310
    },
    {
      "t": 900,
      "x": 478,
      "y": 316
    }
  ],
  "saved_at": "2026-04-29T10:03:00.814579"
}