{
  "session_id": "bot_known_target_captcha_0548_0_1777424585391",
  "image_id": "captcha_0548",
  "target_object": "shoes2",
  "result": "success",
  "duration": 900,
  "click": {
    "x": 106,
    "y": 488,
    "t": 900
  },
  "bbox": {
    "x": 43,
    "y": 425,
    "width": 126,
    "height": 126
  },
  "bot_type": "known_target",
  "mouse_logs": [
    {
      "t": 0,
      "x": 25,
      "y": 169
    },
    {
      "t": 53,
      "x": 30,
      "y": 188
    },
    {
      "t": 106,
      "x": 35,
      "y": 207
    },
    {
      "t": 159,
      "x": 39,
      "y": 225
    },
    {
      "t": 212,
      "x": 44,
      "y": 244
    },
    {
      "t": 265,
      "x": 49,
      "y": 263
    },
    {
      "t": 318,
      "x": 54,
      "y": 282
    },
    {
      "t": 371,
      "x": 58,
      "y": 300
    },
    {
      "t": 424,
      "x": 63,
      "y": 319
    },
    {
      "t": 476,
      "x": 68,
      "y": 338
    },
    {
      "t": 529,
      "x": 73,
      "y": 357
    },
    {
      "t": 582,
      "x": 77,
      "y": 375
    },
    {
      "t": 635,
      "x": 82,
      "y": 394
    },
    {
      "t": 688,
      "x": 87,
      "y": 413
    },
    {
      "t": 741,
      "x": 92,
      "y": 432
    },
    {
      "t": 794,
      "x": 96,
      "y": 450
    },
    {
      "t": 847,
      "x": 101,
      "y": 469
    },
    {
      "t": 900,
      "x": 106,
      "y": 488
    }
  ],
  "saved_at": "2026-04-29T10:03:05.391679"
}