{
  "session_id": "bot_known_target_captcha_0365_0_1777424581893",
  "image_id": "captcha_0365",
  "target_object": "key3",
  "result": "success",
  "duration": 900,
  "click": {
    "x": 507,
    "y": 178,
    "t": 900
  },
  "bbox": {
    "x": 449,
    "y": 120,
    "width": 117,
    "height": 117
  },
  "bot_type": "known_target",
  "mouse_logs": [
    {
      "t": 0,
      "x": 637,
      "y": 515
    },
    {
      "t": 53,
      "x": 629,
      "y": 495
    },
    {
      "t": 106,
      "x": 622,
      "y": 475
    },
    {
      "t": 159,
      "x": 614,
      "y": 456
    },
    {
      "t": 212,
      "x": 606,
      "y": 436
    },
    {
      "t": 265,
      "x": 599,
      "y": 416
    },
    {
      "t": 318,
      "x": 591,
      "y": 396
    },
    {
      "t": 371,
      "x": 583,
      "y": 376
    },
    {
      "t": 424,
      "x": 576,
      "y": 356
    },
    {
      "t": 476,
      "x": 568,
      "y": 337
    },
    {
      "t": 529,
      "x": 561,
      "y": 317
    },
    {
      "t": 582,
      "x": 553,
      "y": 297
    },
    {
      "t": 635,
      "x": 545,
      "y": 277
    },
    {
      "t": 688,
      "x": 538,
      "y": 257
    },
    {
      "t": 741,
      "x": 530,
      "y": 237
    },
    {
      "t": 794,
      "x": 522,
      "y": 218
    },
    {
      "t": 847,
      "x": 515,
      "y": 198
    },
    {
      "t": 900,
      "x": 507,
      "y": 178
    }
  ],
  "saved_at": "2026-04-29T10:03:01.893519"
}