{
  "session_id": "bot_known_target_captcha_0010_2_1777424575455",
  "image_id": "captcha_0010",
  "target_object": "춘식이",
  "result": "success",
  "duration": 900,
  "click": {
    "x": 341,
    "y": 265,
    "t": 900
  },
  "bbox": {
    "x": 294,
    "y": 218,
    "width": 95,
    "height": 94
  },
  "bot_type": "known_target",
  "mouse_logs": [
    {
      "t": 0,
      "x": 618,
      "y": 471
    },
    {
      "t": 53,
      "x": 602,
      "y": 459
    },
    {
      "t": 106,
      "x": 585,
      "y": 447
    },
    {
      "t": 159,
      "x": 569,
      "y": 435
    },
    {
      "t": 212,
      "x": 553,
      "y": 423
    },
    {
      "t": 265,
      "x": 537,
      "y": 410
    },
    {
      "t": 318,
      "x": 520,
      "y": 398
    },
    {
      "t": 371,
      "x": 504,
      "y": 386
    },
    {
      "t": 424,
      "x": 488,
      "y": 374
    },
    {
      "t": 476,
      "x": 471,
      "y": 362
    },
    {
      "t": 529,
      "x": 455,
      "y": 350
    },
    {
      "t": 582,
      "x": 439,
      "y": 338
    },
    {
      "t": 635,
      "x": 422,
      "y": 326
    },
    {
      "t": 688,
      "x": 406,
      "y": 313
    },
    {
      "t": 741,
      "x": 390,
      "y": 301
    },
    {
      "t": 794,
      "x": 374,
      "y": 289
    },
    {
      "t": 847,
      "x": 357,
      "y": 277
    },
    {
      "t": 900,
      "x": 341,
      "y": 265
    }
  ],
  "saved_at": "2026-04-29T10:02:55.455186"
}