{
  "session_id": "bot_known_target_captcha_0214_2_1777424579281",
  "image_id": "captcha_0214",
  "target_object": "cup1",
  "result": "success",
  "duration": 900,
  "click": {
    "x": 82,
    "y": 248,
    "t": 900
  },
  "bbox": {
    "x": 43,
    "y": 209,
    "width": 78,
    "height": 78
  },
  "bot_type": "known_target",
  "mouse_logs": [
    {
      "t": 0,
      "x": 260,
      "y": 254
    },
    {
      "t": 53,
      "x": 250,
      "y": 254
    },
    {
      "t": 106,
      "x": 239,
      "y": 253
    },
    {
      "t": 159,
      "x": 229,
      "y": 253
    },
    {
      "t": 212,
      "x": 218,
      "y": 253
    },
    {
      "t": 265,
      "x": 208,
      "y": 252
    },
    {
      "t": 318,
      "x": 197,
      "y": 252
    },
    {
      "t": 371,
      "x": 187,
      "y": 252
    },
    {
      "t": 424,
      "x": 176,
      "y": 251
    },
    {
      "t": 476,
      "x": 166,
      "y": 251
    },
    {
      "t": 529,
      "x": 155,
      "y": 250
    },
    {
      "t": 582,
      "x": 145,
      "y": 250
    },
    {
      "t": 635,
      "x": 134,
      "y": 250
    },
    {
      "t": 688,
      "x": 124,
      "y": 249
    },
    {
      "t": 741,
      "x": 113,
      "y": 249
    },
    {
      "t": 794,
      "x": 103,
      "y": 249
    },
    {
      "t": 847,
      "x": 92,
      "y": 248
    },
    {
      "t": 900,
      "x": 82,
      "y": 248
    }
  ],
  "saved_at": "2026-04-29T10:02:59.281655"
}