{
  "session_id": "bot_known_target_captcha_0577_0_1777424585902",
  "image_id": "captcha_0577",
  "target_object": "프로도",
  "result": "success",
  "duration": 900,
  "click": {
    "x": 48,
    "y": 548,
    "t": 900
  },
  "bbox": {
    "x": 1,
    "y": 496,
    "width": 94,
    "height": 104
  },
  "bot_type": "known_target",
  "mouse_logs": [
    {
      "t": 0,
      "x": 349,
      "y": 558
    },
    {
      "t": 53,
      "x": 331,
      "y": 557
    },
    {
      "t": 106,
      "x": 314,
      "y": 557
    },
    {
      "t": 159,
      "x": 296,
      "y": 556
    },
    {
      "t": 212,
      "x": 278,
      "y": 556
    },
    {
      "t": 265,
      "x": 260,
      "y": 555
    },
    {
      "t": 318,
      "x": 243,
      "y": 554
    },
    {
      "t": 371,
      "x": 225,
      "y": 554
    },
    {
      "t": 424,
      "x": 207,
      "y": 553
    },
    {
      "t": 476,
      "x": 190,
      "y": 553
    },
    {
      "t": 529,
      "x": 172,
      "y": 552
    },
    {
      "t": 582,
      "x": 154,
      "y": 552
    },
    {
      "t": 635,
      "x": 137,
      "y": 551
    },
    {
      "t": 688,
      "x": 119,
      "y": 550
    },
    {
      "t": 741,
      "x": 101,
      "y": 550
    },
    {
      "t": 794,
      "x": 83,
      "y": 549
    },
    {
      "t": 847,
      "x": 66,
      "y": 549
    },
    {
      "t": 900,
      "x": 48,
      "y": 548
    }
  ],
  "saved_at": "2026-04-29T10:03:05.902054"
}