{
  "session_id": "bot_known_target_captcha_0943_2_1777424592932",
  "image_id": "captcha_0943",
  "target_object": "cup5",
  "result": "success",
  "duration": 900,
  "click": {
    "x": 441,
    "y": 429,
    "t": 900
  },
  "bbox": {
    "x": 400,
    "y": 385,
    "width": 82,
    "height": 89
  },
  "bot_type": "known_target",
  "mouse_logs": [
    {
      "t": 0,
      "x": 693,
      "y": 560
    },
    {
      "t": 53,
      "x": 678,
      "y": 552
    },
    {
      "t": 106,
      "x": 663,
      "y": 545
    },
    {
      "t": 159,
      "x": 649,
      "y": 537
    },
    {
      "t": 212,
      "x": 634,
      "y": 529
    },
    {
      "t": 265,
      "x": 619,
      "y": 521
    },
    {
      "t": 318,
      "x": 604,
      "y": 514
    },
    {
      "t": 371,
      "x": 589,
      "y": 506
    },
    {
      "t": 424,
      "x": 574,
      "y": 498
    },
    {
      "t": 476,
      "x": 560,
      "y": 491
    },
    {
      "t": 529,
      "x": 545,
      "y": 483
    },
    {
      "t": 582,
      "x": 530,
      "y": 475
    },
    {
      "t": 635,
      "x": 515,
      "y": 468
    },
    {
      "t": 688,
      "x": 500,
      "y": 460
    },
    {
      "t": 741,
      "x": 485,
      "y": 452
    },
    {
      "t": 794,
      "x": 471,
      "y": 444
    },
    {
      "t": 847,
      "x": 456,
      "y": 437
    },
    {
      "t": 900,
      "x": 441,
      "y": 429
    }
  ],
  "saved_at": "2026-04-29T10:03:12.932937"
}