{
  "session_id": "bot_known_target_captcha_0289_2_1777424580553",
  "image_id": "captcha_0289",
  "target_object": "cup4",
  "result": "success",
  "duration": 900,
  "click": {
    "x": 756,
    "y": 312,
    "t": 900
  },
  "bbox": {
    "x": 720,
    "y": 276,
    "width": 72,
    "height": 72
  },
  "bot_type": "known_target",
  "mouse_logs": [
    {
      "t": 0,
      "x": 555,
      "y": 313
    },
    {
      "t": 53,
      "x": 567,
      "y": 313
    },
    {
      "t": 106,
      "x": 579,
      "y": 313
    },
    {
      "t": 159,
      "x": 590,
      "y": 313
    },
    {
      "t": 212,
      "x": 602,
      "y": 313
    },
    {
      "t": 265,
      "x": 614,
      "y": 313
    },
    {
      "t": 318,
      "x": 626,
      "y": 313
    },
    {
      "t": 371,
      "x": 638,
      "y": 313
    },
    {
      "t": 424,
      "x": 650,
      "y": 313
    },
    {
      "t": 476,
      "x": 661,
      "y": 312
    },
    {
      "t": 529,
      "x": 673,
      "y": 312
    },
    {
      "t": 582,
      "x": 685,
      "y": 312
    },
    {
      "t": 635,
      "x": 697,
      "y": 312
    },
    {
      "t": 688,
      "x": 709,
      "y": 312
    },
    {
      "t": 741,
      "x": 721,
      "y": 312
    },
    {
      "t": 794,
      "x": 732,
      "y": 312
    },
    {
      "t": 847,
      "x": 744,
      "y": 312
    },
    {
      "t": 900,
      "x": 756,
      "y": 312
    }
  ],
  "saved_at": "2026-04-29T10:03:00.553806"
}