{
  "session_id": "bot_known_target_captcha_0498_2_1777424584442",
  "image_id": "captcha_0498",
  "target_object": "shoes4",
  "result": "success",
  "duration": 900,
  "click": {
    "x": 665,
    "y": 312,
    "t": 900
  },
  "bbox": {
    "x": 603,
    "y": 250,
    "width": 124,
    "height": 124
  },
  "bot_type": "known_target",
  "mouse_logs": [
    {
      "t": 0,
      "x": 638,
      "y": 159
    },
    {
      "t": 53,
      "x": 640,
      "y": 168
    },
    {
      "t": 106,
      "x": 641,
      "y": 177
    },
    {
      "t": 159,
      "x": 643,
      "y": 186
    },
    {
      "t": 212,
      "x": 644,
      "y": 195
    },
    {
      "t": 265,
      "x": 646,
      "y": 204
    },
    {
      "t": 318,
      "x": 648,
      "y": 213
    },
    {
      "t": 371,
      "x": 649,
      "y": 222
    },
    {
      "t": 424,
      "x": 651,
      "y": 231
    },
    {
      "t": 476,
      "x": 652,
      "y": 240
    },
    {
      "t": 529,
      "x": 654,
      "y": 249
    },
    {
      "t": 582,
      "x": 655,
      "y": 258
    },
    {
      "t": 635,
      "x": 657,
      "y": 267
    },
    {
      "t": 688,
      "x": 659,
      "y": 276
    },
    {
      "t": 741,
      "x": 660,
      "y": 285
    },
    {
      "t": 794,
      "x": 662,
      "y": 294
    },
    {
      "t": 847,
      "x": 663,
      "y": 303
    },
    {
      "t": 900,
      "x": 665,
      "y": 312
    }
  ],
  "saved_at": "2026-04-29T10:03:04.442971"
}