{
  "session_id": "bot_known_target_captcha_0012_1_1777424575484",
  "image_id": "captcha_0012",
  "target_object": "key5",
  "result": "success",
  "duration": 900,
  "click": {
    "x": 438,
    "y": 425,
    "t": 900
  },
  "bbox": {
    "x": 391,
    "y": 378,
    "width": 94,
    "height": 94
  },
  "bot_type": "known_target",
  "mouse_logs": [
    {
      "t": 0,
      "x": 369,
      "y": 141
    },
    {
      "t": 53,
      "x": 373,
      "y": 158
    },
    {
      "t": 106,
      "x": 377,
      "y": 174
    },
    {
      "t": 159,
      "x": 381,
      "y": 191
    },
    {
      "t": 212,
      "x": 385,
      "y": 208
    },
    {
      "t": 265,
      "x": 389,
      "y": 225
    },
    {
      "t": 318,
      "x": 393,
      "y": 241
    },
    {
      "t": 371,
      "x": 397,
      "y": 258
    },
    {
      "t": 424,
      "x": 401,
      "y": 275
    },
    {
      "t": 476,
      "x": 406,
      "y": 291
    },
    {
      "t": 529,
      "x": 410,
      "y": 308
    },
    {
      "t": 582,
      "x": 414,
      "y": 325
    },
    {
      "t": 635,
      "x": 418,
      "y": 341
    },
    {
      "t": 688,
      "x": 422,
      "y": 358
    },
    {
      "t": 741,
      "x": 426,
      "y": 375
    },
    {
      "t": 794,
      "x": 430,
      "y": 392
    },
    {
      "t": 847,
      "x": 434,
      "y": 408
    },
    {
      "t": 900,
      "x": 438,
      "y": 425
    }
  ],
  "saved_at": "2026-04-29T10:02:55.484252"
}