{
  "session_id": "bot_known_target_captcha_0909_2_1777424592351",
  "image_id": "captcha_0909",
  "target_object": "라이언",
  "result": "success",
  "duration": 900,
  "click": {
    "x": 142,
    "y": 453,
    "t": 900
  },
  "bbox": {
    "x": 65,
    "y": 357,
    "width": 155,
    "height": 193
  },
  "bot_type": "known_target",
  "mouse_logs": [
    {
      "t": 0,
      "x": 295,
      "y": 166
    },
    {
      "t": 53,
      "x": 286,
      "y": 183
    },
    {
      "t": 106,
      "x": 277,
      "y": 200
    },
    {
      "t": 159,
      "x": 268,
      "y": 217
    },
    {
      "t": 212,
      "x": 259,
      "y": 234
    },
    {
      "t": 265,
      "x": 250,
      "y": 250
    },
    {
      "t": 318,
      "x": 241,
      "y": 267
    },
    {
      "t": 371,
      "x": 232,
      "y": 284
    },
    {
      "t": 424,
      "x": 223,
      "y": 301
    },
    {
      "t": 476,
      "x": 214,
      "y": 318
    },
    {
      "t": 529,
      "x": 205,
      "y": 335
    },
    {
      "t": 582,
      "x": 196,
      "y": 352
    },
    {
      "t": 635,
      "x": 187,
      "y": 369
    },
    {
      "t": 688,
      "x": 178,
      "y": 385
    },
    {
      "t": 741,
      "x": 169,
      "y": 402
    },
    {
      "t": 794,
      "x": 160,
      "y": 419
    },
    {
      "t": 847,
      "x": 151,
      "y": 436
    },
    {
      "t": 900,
      "x": 142,
      "y": 453
    }
  ],
  "saved_at": "2026-04-29T10:03:12.351616"
}