{
  "session_id": "bot_grid_search_captcha_0648_0_1777424587129",
  "image_id": "captcha_0648",
  "target_object": "cup4",
  "result": "success",
  "duration": 240,
  "click": {
    "x": 207,
    "y": 75,
    "t": 240
  },
  "bbox": {
    "x": 153,
    "y": 21,
    "width": 109,
    "height": 109
  },
  "bot_type": "grid_search",
  "mouse_logs": [
    {
      "t": 0,
      "x": 40,
      "y": 40
    },
    {
      "t": 80,
      "x": 120,
      "y": 40
    },
    {
      "t": 160,
      "x": 200,
      "y": 40
    },
    {
      "t": 240,
      "x": 207,
      "y": 75
    }
  ],
  "saved_at": "2026-04-29T10:03:07.129074"
}